{
  "info": {
    "_postman_id": "d298e07a-d3f6-4186-a574-e39f970d3293",
    "name": "Finance Backend API",
    "schema": "https://schema.getpostman.com/json/collection/v2.1.0/collection.json",
    "_exporter_id": "53734149",
    "_collection_link": "https://go.postman.co/collection/53734149-d298e07a-d3f6-4186-a574-e39f970d3293?source=collection_link"
  },
  "item": [
    {
      "name": "Auth",
      "item": [
        {
          "name": "Register",
          "request": {
            "method": "POST",
            "header": [],
            "url": {
              "raw": "http://localhost:5000/api/auth/register",
              "protocol": "http",
              "host": [
                "localhost"
              ],
              "port": "5000",
              "path": [
                "api",
                "auth",
                "register"
              ]
            }
          },
          "response": []
        },
        {
          "name": "Login",
          "request": {
            "method": "POST",
            "header": [],
            "url": {
              "raw": "http://localhost:5000/api/auth/login",
              "protocol": "http",
              "host": [
                "localhost"
              ],
              "port": "5000",
              "path": [
                "api",
                "auth",
                "login"
              ]
            }
          },
          "response": []
        }
      ]
    },
    {
      "name": "Users",
      "item": [
        {
          "name": "Get All Users",
          "request": {
            "method": "GET",
            "header": [],
            "url": {
              "raw": "http://localhost:5000/api/users",
              "protocol": "http",
              "host": [
                "localhost"
              ],
              "port": "5000",
              "path": [
                "api",
                "users"
              ]
            }
          },
          "response": []
        },
        {
          "name": "Update Role",
          "request": {
            "method": "PUT",
            "header": [],
            "url": {
              "raw": "http://localhost:5000/api/users/1/role",
              "protocol": "http",
              "host": [
                "localhost"
              ],
              "port": "5000",
              "path": [
                "api",
                "users",
                "1",
                "role"
              ]
            }
          },
          "response": []
        }
      ]
    },
    {
      "name": "Records",
      "item": [
        {
          "name": "Create Record",
          "request": {
            "method": "POST",
            "header": [],
            "url": {
              "raw": "http://localhost:5000/api/records",
              "protocol": "http",
              "host": [
                "localhost"
              ],
              "port": "5000",
              "path": [
                "api",
                "records"
              ]
            }
          },
          "response": []
        },
        {
          "name": "Get Records",
          "request": {
            "method": "GET",
            "header": [],
            "url": {
              "raw": "http://localhost:5000/api/records",
              "protocol": "http",
              "host": [
                "localhost"
              ],
              "port": "5000",
              "path": [
                "api",
                "records"
              ]
            }
          },
          "response": []
        },
        {
          "name": "Get Records with filters",
          "request": {
            "method": "GET",
            "header": [],
            "url": {
              "raw": "http://localhost:5000/api/records?type=EXPENSE&page=1&limit=2",
              "protocol": "http",
              "host": [
                "localhost"
              ],
              "port": "5000",
              "path": [
                "api",
                "records"
              ],
              "query": [
                {
                  "key": "type",
                  "value": "EXPENSE"
                },
                {
                  "key": "page",
                  "value": "1"
                },
                {
                  "key": "limit",
                  "value": "2"
                }
              ]
            }
          },
          "response": []
        }
      ]
    },
    {
      "name": "Summary",
      "item": [
        {
          "name": "Total Income",
          "request": {
            "method": "GET",
            "header": [],
            "url": {
              "raw": "http://localhost:5000/api/summary/income",
              "protocol": "http",
              "host": [
                "localhost"
              ],
              "port": "5000",
              "path": [
                "api",
                "summary",
                "income"
              ]
            }
          },
          "response": []
        },
        {
          "name": "Total Expense",
          "request": {
            "method": "GET",
            "header": [],
            "url": {
              "raw": "http://localhost:5000/api/summary/expense",
              "protocol": "http",
              "host": [
                "localhost"
              ],
              "port": "5000",
              "path": [
                "api",
                "summary",
                "expense"
              ]
            }
          },
          "response": []
        },
        {
          "name": "Recent Activity",
          "request": {
            "method": "GET",
            "header": [],
            "url": {
              "raw": "http://localhost:5000/api/summary/recent",
              "protocol": "http",
              "host": [
                "localhost"
              ],
              "port": "5000",
              "path": [
                "api",
                "summary",
                "recent"
              ]
            }
          },
          "response": []
        }
      ]
    }
  ],
  "auth": {
    "type": "bearer",
    "bearer": [
      {
        "key": "token",
        "value": "eyJhbGciOiJIUzI1NiIsInR5cCI6IkpXVCJ9.eyJ1c2VySWQiOjIsInJvbGUiOiJBRE1JTiIsImlhdCI6MTc3NTMxMzk2NiwiZXhwIjoxNzc1NDAwMzY2fQ.qzw3CXtt-GU1P_bkUM2SYF-a4dV0RJzo12cxn5geLdc",
        "type": "string"
      }
    ]
  },
  "event": [
    {
      "listen": "prerequest",
      "script": {
        "type": "text/javascript",
        "packages": {},
        "requests": {},
        "exec": [
          ""
        ]
      }
    },
    {
      "listen": "test",
      "script": {
        "type": "text/javascript",
        "packages": {},
        "requests": {},
        "exec": [
          ""
        ]
      }
    }
  ]
}